papipyplug/__init__.py
papipyplug/utils.py
papipyplug-2024.3.4.dist-info/LICENSE
papipyplug-2024.3.4.dist-info/METADATA
papipyplug-2024.3.4.dist-info/WHEEL
papipyplug-2024.3.4.dist-info/top_level.txt
papipyplug-2024.3.4.dist-info/RECORD
