Metadata-Version: 2.1
Name: papipyplug
Version: 2024.3.4
Summary: Utilities to facilitate the conversion of python programs to plugins for use in the dewberry/process-api
Author: Seth Lawler
License: MIT
License-File: LICENSE
